Metadata-Version: 2.4
Name: theoris
Version: 0.5.0
Summary: A Python library for symbolic computation, proof verification, and unit handling
Home-page: https://github.com/OpenOrion/theoris
Author: Open Orion, Inc.
License: MIT
Keywords: symbolic computation,code generation,proof verification
Classifier: Development Status :: 3 - Alpha
Classifier: Intended Audience :: Science/Research
Classifier: License :: OSI Approved :: MIT License
Classifier: Programming Language :: Python :: 3.10
Classifier: Programming Language :: Python :: 3.11
Classifier: Programming Language :: Python :: 3.12
Classifier: Topic :: Scientific/Engineering
Classifier: Topic :: Software Development :: Code Generators
Classifier: Operating System :: OS Independent
Requires-Python: >=3.10
License-File: LICENSE
Requires-Dist: matplotlib>=3.10.1
Requires-Dist: networkx>=3.4.2
Requires-Dist: numpy>=2.2.4
Requires-Dist: sympy==1.10.1
Requires-Dist: pint>=0.24.4
Requires-Dist: nbformat>=5.10.4
Requires-Dist: pysmt>=0.9.5
Requires-Dist: pydantic>=2.11.2
Dynamic: author
Dynamic: classifier
Dynamic: description
Dynamic: description-content-type
Dynamic: home-page
Dynamic: keywords
Dynamic: license
Dynamic: license-file
Dynamic: requires-dist
Dynamic: requires-python
Dynamic: summary
